{
  "users": [
    {
      "id": "6ae9",
      "email": "diego@ufpr.br",
      "username": "diego",
      "password": "1234"
    },
    {
      "name": "Thiago dos Santos",
      "email": "thiago1@ufpr.br",
      "username": "thiago1",
      "password": "123456",
      "gender": "masculino",
      "profileImage": "https://www.github.com/IamThiago-IT.png",
      "id": "7203"
    },
    {
      "id": "1",
      "name": "Admin User",
      "username": "admin",
      "email": "admin@ufpr.br",
      "password": "123456",
      "isAdmin": true,
      "profileImage": "https://www.github.com/IamThiago-IT.png"
    },
    {
      "id": "544f",
      "name": "Luiz",
      "email": "luiz@ufpr.br",
      "username": "LuizAdmin",
      "password": "123456",
      "isAdmin": true
    }
  ],
  "achievements": [
    {
      "id": "1",
      "userId": 1,
      "title": "Primeira Inscrição",
      "description": "Inscreva-se em uma modalidade pela primeira vez.",
      "category": "Modalidades"
    },
    {
      "id": "2",
      "userId": 1,
      "title": "Primeira Meta Concluída",
      "description": "Complete sua primeira meta.",
      "category": "Metas"
    },
    {
      "id": "3",
      "userId": null,
      "title": "Campeão de Torneio",
      "description": "Vença um torneio oficial.",
      "category": "Sistema"
    }
  ],
  "sports": [
    {
      "id": "1",
      "name": "Futebol",
      "description": "Esporte de equipe jogado com uma bola em um campo retangular.",
      "schedule": "Segunda e Quarta - 18:00 às 20:00",
      "location": "Campo Principal"
    },
    {
      "id": "2",
      "name": "Basquete",
      "description": "Esporte de equipe onde o objetivo é marcar pontos jogando a bola através do aro.",
      "schedule": "Terça e Quinta - 16:00 às 18:00",
      "location": "Ginásio"
    },
    {
      "id": "3",
      "name": "Vôlei",
      "description": "Esporte de equipe jogado com uma bola, onde o objetivo é fazer a bola tocar o chão do adversário.",
      "schedule": "Sexta - 18:00 às 20:00",
      "location": "Quadra Coberta"
    }
  ],
  "tournaments": [
    {
      "id": "1",
      "name": "Torneio de Verão",
      "date": "2024-08-01",
      "status": "Concluído",
      "location": "Estádio UFPR",
      "userId": 7203
    },
    {
      "id": "2",
      "name": "Torneio de Inverno",
      "date": "2024-12-01",
      "status": "Em Andamento",
      "location": "Ginásio UFPR",
      "userId": 7203
    }
  ],
  "matches": [
    {
      "id": "1",
      "sport": "Futebol",
      "opponent": "Equipe B",
      "date": "2024-09-14",
      "result": "Vencido"
    },
    {
      "id": "2",
      "sport": "Basquete",
      "opponent": "Time C",
      "date": "2024-09-16",
      "result": "Perdido"
    },
    {
      "id": "3",
      "sport": "Vôlei",
      "opponent": "Equipe A",
      "date": "2024-09-17",
      "result": "Empate"
    }
  ],
  "teams": [
    {
      "id": "1",
      "name": "Equipe A",
      "members": [
        "Alice",
        "Bob",
        "Charlie"
      ],
      "competition": "Campeonato de Verão",
      "status": "Concluída"
    },
    {
      "id": "2",
      "name": "Equipe B",
      "members": [
        "David",
        "Eve",
        "Frank"
      ],
      "competition": "Torneio de Inverno",
      "status": "Em Andamento"
    }
  ],
  "settings": [
    {
      "id": "1",
      "userId": 7203,
      "notifications": true,
      "preferences": false,
      "language": "en",
      "notifyNewPosts": true,
      "notifyLikes": false,
      "notifyNewChampionships": true,
      "notifyComments": false,
      "privacyDetails": true,
      "privacyHistory": true,
      "privacyStats": true,
      "privacyAchievements": true
    }
  ],
  "posts": [
    {
      "id": "7203",
      "author": "Thiago1",
      "date": "2024-08-24",
      "content": "Hoje participei de uma competição incrível! 🎉",
      "image": "https://via.placeholder.com/400x200"
    },
    {
      "id": "2",
      "author": "Maria",
      "date": "2024-08-23",
      "content": "Não vejo a hora do próximo torneio!",
      "image": "https://via.placeholder.com/400x200"
    }
  ],
  "inscricoes": [
    {
      "id": "1",
      "userId": "7203",
      "modalidadeId": "1"
    },
    {
      "id": "2",
      "userId": "1",
      "modalidadeId": "2"
    },
    {
      "id": "cb45",
      "userId": "1",
      "modalidadeId": "1"
    },
    {
      "id": "8be3",
      "userId": "7203",
      "modalidadeId": "2"
    }
  ]
}